Metadata-Version: 2.4
Name: adafruit-circuitpython-displayio-ssd1306
Version: 3.0.4
Summary: DisplayIO driver for SSD1306 monochrome displays
Author-email: Adafruit Industries <circuitpython@adafruit.com>
License: MIT
Project-URL: Homepage, https://github.com/adafruit/Adafruit_CircuitPython_DisplayIO_SSD1306
Keywords: adafruit,blinka,circuitpython,micropython,displayio_ssd1306,displayio,ssd1306,oled
Classifier: Intended Audience :: Developers
Classifier: Topic :: Software Development :: Libraries
Classifier: Topic :: Software Development :: Embedded Systems
Classifier: Topic :: System :: Hardware
Classifier: License :: OSI Approved :: MIT License
Classifier: Programming Language :: Python :: 3
License-File: LICENSE
Requires-Dist: Adafruit-Blinka
Requires-Dist: Adafruit-Blinka-Displayio
Provides-Extra: optional
Dynamic: license-file
